python_syntax/__init__.py
python_syntax/main.py
python_syntax-3.1.dist-info/LICENSE
python_syntax-3.1.dist-info/METADATA
python_syntax-3.1.dist-info/WHEEL
python_syntax-3.1.dist-info/entry_points.txt
python_syntax-3.1.dist-info/top_level.txt
python_syntax-3.1.dist-info/RECORD
