Metadata-Version: 2.1
Name: python-syntax
Version: 3.1
Summary: A CLI tool to insert common Python syntax into files.
Home-page: https://github.com/yourusername/python_syntax
Author: Sandeepan Mohanty
Author-email: sandimohanty@gmail.com
Classifier: Programming Language :: Python :: 3
Classifier: License :: OSI Approved :: MIT License
Classifier: Operating System :: OS Independent
License-File: LICENSE
